{
  "slug": "taj-mahal",
  "title": "Taj Mahal",
  "titleZh": "泰姬陵",
  "level": "W",
  "genre": "Informational",
  "mainSkill": "Key Ideas and Details",
  "questions": [
    {
      "q": {
        "en": "Where is the Taj Mahal located?",
        "zh": "泰姬陵位于哪里？"
      },
      "options": [
        {
          "en": "Agra, Pakistan",
          "zh": "巴基斯坦阿格拉"
        },
        {
          "en": "Nepal",
          "zh": "尼泊尔"
        },
        {
          "en": "Agra, India",
          "zh": "印度阿格拉"
        },
        {
          "en": "Islamabad",
          "zh": "伊斯兰堡"
        }
      ],
      "answer": 2,
      "skill": "Key Ideas and Details",
      "explain": {
        "en": "The book places the Taj Mahal in Agra, India, on the western bank of the Yamuna River.",
        "zh": "书中把泰姬陵置于印度阿格拉，亚穆纳河西岸。"
      }
    },
    {
      "q": {
        "en": "Who built the Taj Mahal and for whom?",
        "zh": "泰姬陵是谁为谁建造的？"
      },
      "options": [
        {
          "en": "The British built it",
          "zh": "英国人建造了它"
        },
        {
          "en": "Akbar built it for his son",
          "zh": "阿克巴为儿子而建"
        },
        {
          "en": "Mumtaz built it for herself according to some versions of the story",
          "zh": "蒙泰姬为自己而建（按书中另一种说法）"
        },
        {
          "en": "Shah Jahan built it for his wife Mumtaz Mahal",
          "zh": "沙贾汗为妻子蒙泰姬·玛哈尔而建"
        }
      ],
      "answer": 3,
      "skill": "Key Ideas and Details",
      "explain": {
        "en": "The fifth Mughal ruler, Shah Jahan, built the Taj Mahal as a memorial for his favorite wife, Mumtaz Mahal.",
        "zh": "莫卧儿第五代君主沙贾汗为最宠爱的妻子蒙泰姬·玛哈尔修建了泰姬陵作为纪念。"
      }
    },
    {
      "q": {
        "en": "When did construction of the Taj Mahal begin, and how long did it take?",
        "zh": "泰姬陵于何时动工，历时多久？"
      },
      "options": [
        {
          "en": "Began 1631, took 1 year",
          "zh": "1631年动工，耗时1年"
        },
        {
          "en": "Began 1700, took 50 years according to some versions of the story",
          "zh": "1700年动工，耗时50年（按书中另一种说法）"
        },
        {
          "en": "Began 1600, took 5 years",
          "zh": "1600年动工，耗时5年"
        },
        {
          "en": "Began 1632, took about 22 years",
          "zh": "1632年动工，耗时约22年"
        }
      ],
      "answer": 3,
      "skill": "Key Ideas and Details",
      "explain": {
        "en": "Construction began in 1632, about a year after Mumtaz's death, and continued for nearly twenty-two years.",
        "zh": "工程于1632年、蒙泰姬去世约一年后动工，持续了近二十二年。"
      }
    },
    {
      "q": {
        "en": "How did Mumtaz Mahal die?",
        "zh": "蒙泰姬·玛哈尔是怎么去世的？"
      },
      "options": [
        {
          "en": "Giving birth to her fourteenth child, at age 38",
          "zh": "在生下第十四个孩子时去世，年仅38岁"
        },
        {
          "en": "In a war",
          "zh": "死于战争"
        },
        {
          "en": "Of old age",
          "zh": "寿终正寝"
        },
        {
          "en": "From the plague according to some versions of the story",
          "zh": "死于瘟疫（按书中另一种说法）"
        }
      ],
      "answer": 0,
      "skill": "Key Ideas and Details",
      "explain": {
        "en": "She died in Shah Jahan's battle camp giving birth to their fourteenth child; she was only thirty-eight.",
        "zh": "她在沙贾汗的军营中因生下第十四个孩子而离世，年仅三十八岁。"
      }
    },
    {
      "q": {
        "en": "What does 'mausoleum' mean in the book?",
        "zh": "书中'mausoleum'是什么意思？"
      },
      "options": [
        {
          "en": "A river",
          "zh": "一条河流"
        },
        {
          "en": "A gate",
          "zh": "一道大门"
        },
        {
          "en": "A large tomb or building containing tombs",
          "zh": "一座大型陵墓或内含墓室建筑"
        },
        {
          "en": "A garden according to some versions of the story",
          "zh": "一座花园（按书中另一种说法）"
        }
      ],
      "answer": 2,
      "skill": "Craft and Structure",
      "explain": {
        "en": "The glossary defines 'mausoleum' as a large tomb or a structure that contains several tombs.",
        "zh": "词汇表将'mausoleum'定义为大型陵墓或内含多处墓室的结构。"
      }
    },
    {
      "q": {
        "en": "What do the four water channels in the garden represent?",
        "zh": "花园里的四条水道象征着什么？"
      },
      "options": [
        {
          "en": "The four heavenly rivers described in the Koran",
          "zh": "《古兰经》中描述的四道天堂之河"
        },
        {
          "en": "The four seasons",
          "zh": "四季"
        },
        {
          "en": "The four Mughal rulers according to some versions of the story",
          "zh": "四位莫卧儿君主（按书中另一种说法）"
        },
        {
          "en": "The four towers",
          "zh": "四座塔楼"
        }
      ],
      "answer": 0,
      "skill": "Key Ideas and Details",
      "explain": {
        "en": "The four channels divide the garden and meet at a pool, symbolizing the four heavenly rivers of the Koran.",
        "zh": "四条水道将花园分隔，在中央汇于水池，象征《古兰经》中的四道天堂之河。"
      }
    },
    {
      "q": {
        "en": "After the Shah's death, what damaged the Taj Mahal before the British restored it?",
        "zh": "在沙贾汗去世后、英国人修复之前，是什么损毁了泰姬陵？"
      },
      "options": [
        {
          "en": "A flood washed it away",
          "zh": "洪水把它冲走了"
        },
        {
          "en": "Thieves took the gems and decorations; it was practically abandoned",
          "zh": "盗贼偷走了宝石与装饰；它几乎被废弃"
        },
        {
          "en": "A fire burned the marble according to some versions of the story in an early draft of the book",
          "zh": "大火烧毁了大理石（按书中另一种说法）（在书的早期草稿中）"
        },
        {
          "en": "An earthquake destroyed it",
          "zh": "地震摧毁了它"
        }
      ],
      "answer": 1,
      "skill": "Integration of Knowledge and Ideas",
      "explain": {
        "en": "After the Shah's death the monument was neglected and thieves stripped many gems and decorations before British restoration.",
        "zh": "君主去世后，陵墓遭荒废，盗贼掠走许多宝石装饰，直到英国人进行修复。"
      }
    },
    {
      "q": {
        "en": "Why does the author mention 'marble cancer' and air pollution?",
        "zh": "作者为什么要提到“大理石癌症”和空气污染？"
      },
      "options": [
        {
          "en": "To describe a hospital",
          "zh": "为了描写一家医院"
        },
        {
          "en": "To explain the modern threats the monument faces and why it needs protection",
          "zh": "为了说明这座纪念碑面临的现代威胁，以及它为何需要保护"
        },
        {
          "en": "To advertise cleaning products according to some versions of the story in an early draft of the book",
          "zh": "为了给清洁用品打广告（按书中另一种说法）（在书的早期草稿中）"
        },
        {
          "en": "To prove the Taj is ugly",
          "zh": "为了证明泰姬陵很丑"
        }
      ],
      "answer": 1,
      "skill": "Author's Purpose and Perspective",
      "explain": {
        "en": "The author lists pollution, 'marble cancer,' and visitor wear to show why India protects the monument with traffic-free zones.",
        "zh": "作者列举污染、“大理石癌症”和游客磨损，以说明印度为何要用禁行区等措施保护它。"
      }
    },
    {
      "q": {
        "en": "What recognition does the book say the Taj Mahal has received?",
        "zh": "本书说泰姬陵获得了什么认可？"
      },
      "options": [
        {
          "en": "It is a UNESCO World Heritage Site and one of the New Seven Wonders",
          "zh": "它是联合国教科文组织世界遗产，也是“世界新七大奇迹”之一"
        },
        {
          "en": "It is a U.S. national park",
          "zh": "它是一座美国国家公园"
        },
        {
          "en": "It is the tallest building in the world according to some versions of the story",
          "zh": "它是世界上最高的建筑（按书中另一种说法）"
        },
        {
          "en": "It won a Nobel Prize",
          "zh": "它获得了诺贝尔奖"
        }
      ],
      "answer": 0,
      "skill": "Key Ideas and Details",
      "explain": {
        "en": "The UN declared it a World Heritage Site and an international vote named it one of the New Seven Wonders.",
        "zh": "联合国将其列为世界遗产，国际投票也把它评为“世界新七大奇迹”之一。"
      }
    },
    {
      "q": {
        "en": "According to the 'Amazing Facts,' about how much would it cost to build the Taj Mahal today?",
        "zh": "根据“惊人事实”，如今重建泰姬陵大约要花多少钱？"
      },
      "options": [
        {
          "en": "About $100 billion according to some versions of the story",
          "zh": "约1000亿美元（按书中另一种说法）"
        },
        {
          "en": "About $1.6 billion - four times the cost of Disney World",
          "zh": "约16亿美元——是迪士尼世界造价的四倍"
        },
        {
          "en": "About $1,000",
          "zh": "约1000美元"
        },
        {
          "en": "About $32 million",
          "zh": "约3200万美元"
        }
      ],
      "answer": 1,
      "skill": "Integration of Knowledge and Ideas",
      "explain": {
        "en": "The book states building it today would cost about $1.6 billion, four times the cost of Disney World.",
        "zh": "书中说，如今重建约需16亿美元，是迪士尼世界造价的四倍。"
      }
    }
  ],
  "extended": {
    "prompt": {
      "en": "The Taj Mahal was built as a memorial of love. Do you agree it should be one of the New Seven Wonders? Write a short opinion essay using evidence from the book.",
      "zh": "泰姬陵是作为爱的纪念而建。你同意它入选“世界新七大奇迹”吗？请运用书中证据写一篇简短的议论短文。"
    },
    "guidance": {
      "en": [
        "State your opinion clearly in the first sentence.",
        "Support it with two or three facts from the book, such as its design, cost, or history."
      ],
      "zh": [
        "在第一句话中就清楚表明你的观点。",
        "用书中两到三个事实（如设计、造价或历史）来支撑你的观点。"
      ]
    }
  }
}