{
  "slug": "komodo-dragons-giant-reptiles",
  "title": "Komodo Dragons Giant Reptiles",
  "titleZh": "科莫多龙：巨型爬行动物",
  "level": "X",
  "genre": "Animal",
  "mainSkill": "Key Ideas and Details",
  "questions": [
    {
      "q": {
        "en": "About how big do adult Komodo dragons get?",
        "zh": "成年科莫多龙大约有多大？"
      },
      "options": [
        {
          "en": "About 10 feet (3 m) long and 176 pounds (80 kg).",
          "zh": "约10英尺（3米）长，176磅（80公斤）。"
        },
        {
          "en": "About 20 feet (6 m) long and 500 pounds (227 kg).",
          "zh": "约20英尺（6米）长，500磅（227公斤）。"
        },
        {
          "en": "About 6 feet (1.8 m) tall and 176 pounds (80 kg), like a human.",
          "zh": "约6英尺（1.8米）高，176磅（80公斤），和人类一样。"
        },
        {
          "en": "About 3 feet (1 m) long and 20 pounds (9 kg).",
          "zh": "约3英尺（1米）长，20磅（9公斤）。"
        }
      ],
      "answer": 0,
      "skill": "Key Ideas and Details",
      "explain": {
        "en": "The 'How Big Is It?' box lists the Komodo dragon as length 10 feet (3 m), weight 176 pounds (80 kg).",
        "zh": "书中'它有多大？'的图示标明科莫多龙体长10英尺（3米），重176磅（80公斤）。"
      }
    },
    {
      "q": {
        "en": "Where do all wild Komodo dragons live?",
        "zh": "所有野生的科莫多龙生活在哪里？"
      },
      "options": [
        {
          "en": "On Madagascar.",
          "zh": "在马达加斯加。"
        },
        {
          "en": "On five of the Lesser Sunda Islands in Indonesia.",
          "zh": "在印度尼西亚的五个小巽他群岛上。"
        },
        {
          "en": "In Australia.",
          "zh": "在澳大利亚。"
        },
        {
          "en": "On the Galápagos Islands. according to some versions of the story",
          "zh": "在加拉帕戈斯群岛。（按书中另一种说法）"
        }
      ],
      "answer": 1,
      "skill": "Key Ideas and Details",
      "explain": {
        "en": "The book says Indonesia 'is home to all wild Komodo dragons' and they live 'on five of the Lesser Sunda Islands.'",
        "zh": "书中说印度尼西亚'是所有野生科莫多龙的家园'，它们生活在'五个小巽他群岛'上。"
      }
    },
    {
      "q": {
        "en": "What are the main foods of Komodo dragons, which were introduced to the islands by humans?",
        "zh": "科莫多龙的主要食物是什么？这些动物是人类引入岛屿的。"
      },
      "options": [
        {
          "en": "Deer, wild pigs, and water buffalo.",
          "zh": "鹿、野猪和水牛。"
        },
        {
          "en": "Fish exclusively.",
          "zh": "只有鱼。"
        },
        {
          "en": "Only fruit and plants. according to some versions of the story",
          "zh": "只有水果和植物。（按书中另一种说法）"
        },
        {
          "en": "Only small birds.",
          "zh": "只有小鸟。"
        }
      ],
      "answer": 0,
      "skill": "Key Ideas and Details",
      "explain": {
        "en": "The book states their main foods are 'deer, wild pigs, and water buffalo, all of which have been introduced to the Lesser Sunda Islands by humans.'",
        "zh": "书中说它们的主要食物是'鹿、野猪和水牛，这些都是人类引入小巽他群岛的'。"
      }
    },
    {
      "q": {
        "en": "What did scientists recently discover about Komodo dragons?",
        "zh": "科学家最近发现了科莫多龙的什么特点？"
      },
      "options": [
        {
          "en": "That they lay their eggs in water.",
          "zh": "它们在水里产卵。"
        },
        {
          "en": "That they are warm-blooded.",
          "zh": "它们是温血动物。"
        },
        {
          "en": "That they can fly short distances. according to some versions of the story in an early draft of the book",
          "zh": "它们能短距离飞行。（按书中另一种说法）（在书的早期草稿中）"
        },
        {
          "en": "That they have venom delivered with their bites, which stops blood from clotting and causes shock.",
          "zh": "它们的咬伤带有毒液，能阻止血液凝固并导致休克。"
        }
      ],
      "answer": 3,
      "skill": "Key Ideas and Details",
      "explain": {
        "en": "The book says scientists 'recently discovered that Komodo dragons have venom' that speeds blood loss by preventing clotting and causes shock.",
        "zh": "书中说科学家'最近发现科莫多龙有毒液'，能阻止血液凝固以加速失血并导致休克。"
      }
    },
    {
      "q": {
        "en": "How does a Komodo dragon use its long, forked tongue to find dead prey?",
        "zh": "科莫多龙如何利用它细长的分叉舌头寻找死去的猎物？"
      },
      "options": [
        {
          "en": "It digs burrows with it.",
          "zh": "它用舌头挖洞。"
        },
        {
          "en": "It uses the tongue to build its nest.",
          "zh": "它用舌头筑巢。"
        },
        {
          "en": "It uses the tongue to swim between islands. according to some versions of the story in an early draft of the book as mentioned in a later chapter before the main events begin",
          "zh": "它用舌头在岛屿间游水。（按书中另一种说法）（在书的早期草稿中）（正如后文某一章提到的）（在主要事件发生之前）"
        },
        {
          "en": "It flicks the tongue to 'taste' the air, then touches the two tips to an organ on the roof of its mouth to tell which direction the odor comes from.",
          "zh": "它弹动舌头'品尝'空气，再把两个舌尖触到口腔顶部的器官，以判断气味来自哪个方向。"
        }
      ],
      "answer": 3,
      "skill": "Integration of Knowledge and Ideas",
      "explain": {
        "en": "The text explains the dragon flicks its forked tongue to sample airborne molecules, then touches them to a special organ on the roof of its mouth to find the direction of dead animals.",
        "zh": "文中解释，龙弹动分叉舌头采集空气中的分子，再触到口腔顶部的特殊器官，从而判断死动物的方向。"
      }
    },
    {
      "q": {
        "en": "Why are the Komodo dragons on Gili Motang and Gili Dasami much smaller than those on the other islands?",
        "zh": "为什么吉利莫唐岛和吉利达萨米岛上的科莫多龙比其他岛上的小很多？"
      },
      "options": [
        {
          "en": "They live in colder ocean water.",
          "zh": "它们生活在更冷的海水里。"
        },
        {
          "en": "Over time they became smaller as a way of adapting to less food and a harsher environment.",
          "zh": "随着时间的推移，它们变小以适应更少的食物和更恶劣的环境。"
        },
        {
          "en": "They are a completely different species. according to some versions of the story in an early draft of the book",
          "zh": "它们是完全不同的物种。（按书中另一种说法）（在书的早期草稿中）"
        },
        {
          "en": "They are just baby dragons.",
          "zh": "它们只是幼龙。"
        }
      ],
      "answer": 1,
      "skill": "Integration of Knowledge and Ideas",
      "explain": {
        "en": "The book says on those two islands 'these dragons have become smaller as a way of adapting to less food and a harsher environment.'",
        "zh": "书中说，在那两个岛上'这些龙变得更小，是对更少食物和更恶劣环境的一种适应'。"
      }
    },
    {
      "q": {
        "en": "In the glossary, what does 'serrated' mean?",
        "zh": "词汇表中，'serrated'（锯齿状的）是什么意思？"
      },
      "options": [
        {
          "en": "Tending to live alone. according to some versions of the story",
          "zh": "倾向于独居。（按书中另一种说法）"
        },
        {
          "en": "Related to bacteria.",
          "zh": "与细菌有关。"
        },
        {
          "en": "Having a jagged or saw-toothed edge.",
          "zh": "具有锯齿状或像锯齿一样的边缘。"
        },
        {
          "en": "Smooth and flat.",
          "zh": "平滑而扁平。"
        }
      ],
      "answer": 2,
      "skill": "Craft and Structure",
      "explain": {
        "en": "The glossary defines 'serrated' as 'having a jagged or tooth-shaped edge; saw-toothed'—used to describe the dragons' teeth.",
        "zh": "词汇表把 serrated 定义为'具有锯齿状或齿状边缘；如锯子般'，用来描述龙的牙齿。"
      }
    },
    {
      "q": {
        "en": "What is the author's main purpose in writing this book?",
        "zh": "作者写这本书的主要目的是什么？"
      },
      "options": [
        {
          "en": "To teach readers how to cook a Komodo dragon.",
          "zh": "教读者如何烹饪科莫多龙。"
        },
        {
          "en": "To inform readers about the biology, habitat, and conservation of Komodo dragons.",
          "zh": "向读者介绍科莫多龙的生物特征、栖息地与保护状况。"
        },
        {
          "en": "To persuade readers to keep a Komodo dragon as a pet. according to some versions of the story",
          "zh": "劝说读者把科莫多龙当宠物养。（按书中另一种说法）"
        },
        {
          "en": "To tell a made-up adventure story about a dragon.",
          "zh": "讲一个关于龙的虚构冒险故事。"
        }
      ],
      "answer": 1,
      "skill": "Author's Purpose and Perspective",
      "explain": {
        "en": "The book is an informational text covering the dragons' size, body features, hunting, babies, and conservation efforts such as Komodo National Park.",
        "zh": "这是一本科普读物，内容涵盖龙体型、身体特征、捕猎、幼龙以及科莫多国家公园等保护工作。"
      }
    },
    {
      "q": {
        "en": "What is the conservation status of Komodo dragons, and about how many live in the wild?",
        "zh": "科莫多龙的保护现状如何？野外大约有多少只？"
      },
      "options": [
        {
          "en": "Vulnerable, with about 3,000 to 5,000 living in the wild.",
          "zh": "易危，野外约有3,000到5,000只。"
        },
        {
          "en": "Endangered, with fewer than 50 left. according to some versions of the story",
          "zh": "濒危，只剩下不到50只。（按书中另一种说法）"
        },
        {
          "en": "Common, with millions in the wild.",
          "zh": "常见，野外的有数百万只。"
        },
        {
          "en": "Extinct, with none left in the wild.",
          "zh": "已灭绝，野外一只不剩。"
        }
      ],
      "answer": 0,
      "skill": "Key Ideas and Details",
      "explain": {
        "en": "The book states 'Only 3,000 to 5,000 Komodo dragons live in the wild' and their status is 'vulnerable.'",
        "zh": "书中说'野外只有3,000到5,000只科莫多龙'，其保护现状为'易危'。"
      }
    },
    {
      "q": {
        "en": "When do baby Komodo dragons hatch, and how do they stay safe?",
        "zh": "小科莫多龙在什么时候孵化？它们如何保护自己？"
      },
      "options": [
        {
          "en": "At the start of the dry season, and they live only in burrows underground. according to some versions of the story",
          "zh": "在旱季开始时孵化，只住在地下洞穴里。（按书中另一种说法）"
        },
        {
          "en": "In summer, and they are guarded by their mother in the nest.",
          "zh": "在夏天孵化，由母亲在巢中守护。"
        },
        {
          "en": "At the end of the rainy season in April, and they climb trees to stay safe from adult dragons and hawks.",
          "zh": "在雨季结束的4月孵化，它们爬到树上躲避成年龙和鹰。"
        },
        {
          "en": "In the middle of winter, and they stay in the water.",
          "zh": "在隆冬孵化，它们待在水里。"
        }
      ],
      "answer": 2,
      "skill": "Key Ideas and Details",
      "explain": {
        "en": "The book says babies 'hatch at the end of the rainy season in April' and 'climb trees to stay safe from adult dragons and other predators, especially hawks.'",
        "zh": "书中说幼龙'在雨季结束的4月孵化'，并'爬到树上躲避成年龙和其他捕食者，尤其是鹰'。"
      }
    }
  ],
  "extended": {
    "prompt": {
      "en": "The book's Focus Question asks how a Komodo dragon's unique features help it survive. Choose two features (such as its venom, forked tongue, or ambush hunting) and explain in your own words how each one helps the dragon catch food and stay alive in its island home.",
      "zh": "本书的焦点问题问的是：科莫多龙的独特特征如何帮助它生存？请挑选两个特征（比如毒液、分叉舌头或伏击捕猎），用自己的话说明每一个如何帮助它在岛上捕食和存活。"
    },
    "guidance": {
      "en": [
        "Use the 'Deadly Predators' section: venom stops clotting and causes shock, while bacteria in the mouth can cause deadly infection.",
        "Use the forked-tongue description and the ambush strategy along game trails to explain how dragons locate and overpower prey."
      ],
      "zh": [
        "参考'致命的捕食者'一节：毒液阻止血液凝固并引起休克，而口腔中的细菌可造成致命感染。",
        "运用分叉舌头和沿动物小径伏击的描述，说明龙如何定位并制服猎物。"
      ]
    }
  }
}