{
  "slug": "whale-sharks-giant-fish",
  "title": "Whale Sharks: Giant Fish",
  "titleZh": "鲸鲨：巨大的鱼",
  "level": "R",
  "genre": "Informational",
  "mainSkill": "Key Ideas and Details",
  "questions": [
    {
      "q": {
        "en": "What is the whale shark?",
        "zh": "鲸鲨是什么？"
      },
      "options": [
        {
          "en": "A type of whale that breathes air.",
          "zh": "一种用肺呼吸的鲸鱼。"
        },
        {
          "en": "A small tropical fish that lives in ponds. according to some versions of the story",
          "zh": "生活在池塘里的小型热带鱼。（按书中另一种说法）"
        },
        {
          "en": "The biggest fish in the sea, and the biggest shark in the world.",
          "zh": "海洋中最大的鱼，也是世界上最大的鲨鱼。"
        },
        {
          "en": "An octopus that changes color.",
          "zh": "会变颜色的章鱼。"
        }
      ],
      "answer": 2,
      "skill": "Key Ideas and Details",
      "explain": {
        "en": "The book says: 'The biggest shark in the world—also the biggest fish—is a gentle giant.'",
        "zh": "书中说：“世界上最大的鲨鱼——也是最大的鱼——是一位温柔的巨人。”"
      }
    },
    {
      "q": {
        "en": "What do whale sharks mainly eat?",
        "zh": "鲸鲨主要吃什么？"
      },
      "options": [
        {
          "en": "Other sharks and large fish. according to some versions of the story",
          "zh": "其他鲨鱼和大型鱼类。（按书中另一种说法）"
        },
        {
          "en": "Only seaweed.",
          "zh": "只吃海藻。"
        },
        {
          "en": "Large seals and penguins.",
          "zh": "大型海豹和企鹅。"
        },
        {
          "en": "Tiny ocean animals that drift in the water, such as krill.",
          "zh": "水中漂浮的微小海洋动物，比如磷虾。"
        }
      ],
      "answer": 3,
      "skill": "Key Ideas and Details",
      "explain": {
        "en": "The book states whale sharks 'eat tiny ocean animals that drift or swim in the water. Krill ... are among their favorite foods.'",
        "zh": "书中说鲸鲨“吃水中漂浮或游动的微小海洋动物。磷虾……是它们最喜欢的食物之一。”"
      }
    },
    {
      "q": {
        "en": "How do whale sharks collect their food?",
        "zh": "鲸鲨是如何获取食物的？"
      },
      "options": [
        {
          "en": "By using venom to stun prey.",
          "zh": "用毒液麻痹猎物。"
        },
        {
          "en": "By filter feeding—water flows in and filter pads catch the small animals.",
          "zh": "通过滤食——水流入，过滤垫挡住小动物。"
        },
        {
          "en": "By hunting other animals with sharp teeth like most sharks. according to some versions of the story",
          "zh": "像大多数鲨鱼那样用尖牙捕猎其他动物。（按书中另一种说法）"
        },
        {
          "en": "By trapping fish in nets they build.",
          "zh": "用自己织的网困住鱼。"
        }
      ],
      "answer": 1,
      "skill": "Key Ideas and Details",
      "explain": {
        "en": "The book explains: 'Whale sharks use a process called filter feeding to collect food.'",
        "zh": "书中解释：“鲸鲨用一种叫做滤食的方式获取食物。”"
      }
    },
    {
      "q": {
        "en": "What does the word 'migrate' mean as used in the book?",
        "zh": "书中“migrate（迁徙）”一词是什么意思？"
      },
      "options": [
        {
          "en": "To move from one region to another, often long distances.",
          "zh": "从一个地区移动到另一个地区，常常距离很远。"
        },
        {
          "en": "To change body color.",
          "zh": "改变身体颜色。"
        },
        {
          "en": "To lay eggs in a nest.",
          "zh": "在巢里产卵。"
        },
        {
          "en": "To sleep through the winter. according to some versions of the story",
          "zh": "整个冬天冬眠。（按书中另一种说法）"
        }
      ],
      "answer": 0,
      "skill": "Craft and Structure",
      "explain": {
        "en": "The glossary defines migrate as 'to move from one habitat or region to another at a certain time.'",
        "zh": "词汇表把 migrate 定义为“在某个特定时间从一个栖息地或地区移动到另一个”。"
      }
    },
    {
      "q": {
        "en": "How is a whale shark's swimming different from most other sharks?",
        "zh": "鲸鲨的游动方式与大多数其他鲨鱼有什么不同？"
      },
      "options": [
        {
          "en": "It uses its whole body to swim, not just its tail and back end.",
          "zh": "它用整个身体游泳，而不只是用尾巴和后半身。"
        },
        {
          "en": "It cannot move its tail at all. according to some versions of the story",
          "zh": "它完全无法摆动尾巴。（按书中另一种说法）"
        },
        {
          "en": "It has no fins.",
          "zh": "它没有鳍。"
        },
        {
          "en": "It swims only backward.",
          "zh": "它只倒着游。"
        }
      ],
      "answer": 0,
      "skill": "Craft and Structure",
      "explain": {
        "en": "The book says: 'A whale shark uses its whole body to swim—not just its tail and back end like other sharks.'",
        "zh": "书中说：“鲸鲨用整个身体游泳——不像其他鲨鱼那样只用尾巴和后半身。”"
      }
    },
    {
      "q": {
        "en": "Why are remoras often seen with whale sharks?",
        "zh": "为什么鲸鲨身边常常能看到䲟鱼？"
      },
      "options": [
        {
          "en": "They are actually the same species.",
          "zh": "它们其实是同一种生物。"
        },
        {
          "en": "Remoras use the shark as their food.",
          "zh": "䲟鱼把鲨鱼当食物。"
        },
        {
          "en": "Remoras eat parasites off the shark's skin and get protection in return.",
          "zh": "䲟鱼吃掉鲨鱼皮肤上的寄生虫，作为回报获得保护。"
        },
        {
          "en": "Remoras attack and eat the whale shark. according to some versions of the story",
          "zh": "䲟鱼攻击并吃掉鲸鲨。（按书中另一种说法）"
        }
      ],
      "answer": 2,
      "skill": "Integration of Knowledge and Ideas",
      "explain": {
        "en": "The book explains remoras 'attach themselves to whale sharks and eat parasites off their skin.'",
        "zh": "书中解释䲟鱼“附着在鲸鲨身上，吃掉它们皮肤上的寄生虫。”"
      }
    },
    {
      "q": {
        "en": "Scientists think whale sharks find their food mainly by which sense?",
        "zh": "科学家认为鲸鲨主要靠哪种感官寻找食物？"
      },
      "options": [
        {
          "en": "Smell.",
          "zh": "嗅觉。"
        },
        {
          "en": "Hearing.",
          "zh": "听觉。"
        },
        {
          "en": "Touch.",
          "zh": "触觉。"
        },
        {
          "en": "Electricity.",
          "zh": "电流感应。"
        }
      ],
      "answer": 0,
      "skill": "Integration of Knowledge and Ideas",
      "explain": {
        "en": "The book says: 'Whale sharks probably find their food by smell,' based on where their nostrils and eyes are located.",
        "zh": "书中说：“鲸鲨很可能靠嗅觉寻找食物”，这是根据它们鼻孔和眼睛的位置判断的。"
      }
    },
    {
      "q": {
        "en": "What is the author's main purpose in writing about whale sharks?",
        "zh": "作者写鲸鲨的主要目的是什么？"
      },
      "options": [
        {
          "en": "To argue that sharks should be removed from the oceans. according to some versions of the story",
          "zh": "主张应该把鲨鱼从海洋中清除。（按书中另一种说法）"
        },
        {
          "en": "To explain how to cook shark meat.",
          "zh": "解释如何烹饪鲨鱼肉。"
        },
        {
          "en": "To show that all sharks are dangerous.",
          "zh": "说明所有鲨鱼都很危险。"
        },
        {
          "en": "To describe the whale shark's traits and its gentle nature.",
          "zh": "描述鲸鲨的特征以及它温和的天性。"
        }
      ],
      "answer": 3,
      "skill": "Author's Purpose and Perspective",
      "explain": {
        "en": "The book focuses on the whale shark's size, traits, and peaceful behavior as 'gentle giants.'",
        "zh": "这本书聚焦于鲸鲨的体型、特征，以及它作为“温柔的巨人”的平和行为。"
      }
    },
    {
      "q": {
        "en": "How does the author describe the whale shark's personality?",
        "zh": "作者如何描述鲸鲨的“性格”？"
      },
      "options": [
        {
          "en": "Lazy and not very smart.",
          "zh": "懒惰又不聪明。"
        },
        {
          "en": "Peaceful and slow-moving—a 'gentle giant.'",
          "zh": "平和而缓慢移动——一位“温柔的巨人”。"
        },
        {
          "en": "Extremely fast and violent.",
          "zh": "极快又暴烈。"
        },
        {
          "en": "Frightening and aggressive. according to some versions of the story",
          "zh": "可怕又具攻击性。（按书中另一种说法）"
        }
      ],
      "answer": 1,
      "skill": "Author's Purpose and Perspective",
      "explain": {
        "en": "The book calls it 'peaceful and slow moving' and 'truly ... gentle giants.'",
        "zh": "书中称它“平和而缓慢移动”，是“真正的……温柔的巨人”。"
      }
    },
    {
      "q": {
        "en": "According to the book, what may help keep young whale sharks safe?",
        "zh": "根据这本书，什么可能帮助年幼的鲸鲨保持安全？"
      },
      "options": [
        {
          "en": "Their loud roar.",
          "zh": "它们响亮的吼叫声。"
        },
        {
          "en": "Their checkerboard-like color pattern may help camouflage or shield them.",
          "zh": "它们像棋盘一样的花纹可能有助于伪装或保护它们。"
        },
        {
          "en": "Their ability to fly.",
          "zh": "它们会飞的能力。"
        },
        {
          "en": "Living only in fresh water. according to some versions of the story in an early draft of the book",
          "zh": "只生活在淡水中。（按书中另一种说法）（在书的早期草稿中）"
        }
      ],
      "answer": 1,
      "skill": "Author's Purpose and Perspective",
      "explain": {
        "en": "The book says the color pattern 'may help keep young whale sharks safe' and 'may also help shield whale sharks from too much sunlight.'",
        "zh": "书中说这种花纹“可能帮助保护年幼的鲸鲨安全”，也“可能帮助鲸鲨遮挡过强的阳光”。"
      }
    }
  ],
  "extended": {
    "prompt": {
      "en": "Choose one trait of the whale shark (such as its filter feeding, color pattern, or size) and write a paragraph explaining how that trait helps it survive in the ocean.",
      "zh": "选择鲸鲨的一个特征（如滤食方式、花纹或体型），写一段话说明这个特征如何帮助它在海洋中生存。"
    },
    "guidance": {
      "en": [
        "Name the trait clearly in your first sentence.",
        "Use facts from the book, like its 300 rows of tiny teeth or 5-foot-wide mouth, to support your idea."
      ],
      "zh": [
        "在第一句话中清楚地写出这个特征。",
        "用书中提到的事实来支持你的观点，比如它有300排细小的牙齿或宽达5英尺的嘴。"
      ]
    }
  }
}