{
  "slug": "rent-a-llama",
  "title": "Rent a Llama",
  "titleZh": "租一只羊驼",
  "level": "P",
  "genre": "Fiction",
  "mainSkill": "Craft and Structure",
  "questions": [
    {
      "q": {
        "en": "What is the main idea of the story?",
        "zh": "这个故事的主旨是什么？"
      },
      "options": [
        {
          "en": "A family rents a llama for a special job",
          "zh": "一家人租了一只羊驼来完成一项特别的任务"
        },
        {
          "en": "A llama runs away from home",
          "zh": "一只羊驼离家出走"
        },
        {
          "en": "A boy buys a car",
          "zh": "一个男孩买了一辆汽车"
        },
        {
          "en": "A cat learns to swim",
          "zh": "一只猫学会了游泳"
        }
      ],
      "answer": 0,
      "skill": "Key Ideas and Details",
      "explain": {
        "en": "The story follows a family that rents a llama, showing how the animal helps them with a task.",
        "zh": "故事讲述一家人租了一只羊驼，展现这只动物如何帮助他们完成一项任务。"
      }
    },
    {
      "q": {
        "en": "Why does the family decide to rent a llama?",
        "zh": "这家人为什么决定租一只羊驼？"
      },
      "options": [
        {
          "en": "Because they need help with carrying or a job",
          "zh": "因为他们需要帮助来搬运东西或完成一项工作"
        },
        {
          "en": "Because they want a pet to sleep with",
          "zh": "因为他们想要一只陪睡的宠物"
        },
        {
          "en": "Because they are opening a school",
          "zh": "因为他们正在开办一所学校"
        },
        {
          "en": "Because they lost their dog",
          "zh": "因为他们弄丢了狗"
        }
      ],
      "answer": 0,
      "skill": "Key Ideas and Details",
      "explain": {
        "en": "The book shows the family renting a llama because they need an animal that can help with work, such as carrying loads.",
        "zh": "书中展现这家人租羊驼是因为他们需要一只能帮忙干活的动物，比如搬运重物。"
      }
    },
    {
      "q": {
        "en": "What does the word 'rent' mean in this story?",
        "zh": "在这个故事中，“租”这个词是什么意思？"
      },
      "options": [
        {
          "en": "To pay to use something for a while",
          "zh": "付钱在一段时间内使用某物"
        },
        {
          "en": "To give something away for free",
          "zh": "免费送出某物"
        },
        {
          "en": "To throw something away",
          "zh": "把某物扔掉"
        },
        {
          "en": "To build something new",
          "zh": "建造新东西"
        }
      ],
      "answer": 0,
      "skill": "Craft and Structure",
      "explain": {
        "en": "The story uses 'rent' to mean paying for the temporary use of the llama rather than buying it.",
        "zh": "故事中“租”指的是付钱临时使用羊驼，而不是买下它。"
      }
    },
    {
      "q": {
        "en": "How does the llama help the characters?",
        "zh": "羊驼是如何帮助故事中的角色的？"
      },
      "options": [
        {
          "en": "By carrying things as they walk",
          "zh": "通过在行走时帮他们驮东西"
        },
        {
          "en": "By cooking dinner",
          "zh": "通过做晚饭"
        },
        {
          "en": "By driving a bus",
          "zh": "通过开公交车"
        },
        {
          "en": "By painting a house",
          "zh": "通过粉刷房子"
        }
      ],
      "answer": 0,
      "skill": "Key Ideas and Details",
      "explain": {
        "en": "The book describes the llama carrying packs or loads, making the family's work easier as they travel.",
        "zh": "书中描写羊驼驮着包裹或重物，让这家人行走时的工作更轻松。"
      }
    },
    {
      "q": {
        "en": "What problem do the characters face on their trip?",
        "zh": "角色们在旅途中遇到了什么问题？"
      },
      "options": [
        {
          "en": "The load is too heavy to carry alone",
          "zh": "行李太重，一个人搬不动"
        },
        {
          "en": "It starts to snow indoors",
          "zh": "室内开始下雪"
        },
        {
          "en": "They forget how to read",
          "zh": "他们忘了怎么阅读"
        },
        {
          "en": "Their car breaks down",
          "zh": "他们的汽车坏了"
        }
      ],
      "answer": 0,
      "skill": "Key Ideas and Details",
      "explain": {
        "en": "The story shows the family struggling with a heavy load, which is why renting a strong llama solves their problem.",
        "zh": "故事展现这家人被沉重的行李所困扰，这正是他们租一只强壮羊驼来解决问题的原因。"
      }
    },
    {
      "q": {
        "en": "How does the story show the llama's personality?",
        "zh": "故事是如何展现羊驼的性格的？"
      },
      "options": [
        {
          "en": "By describing its calm and helpful behavior",
          "zh": "通过描写它冷静而乐于助人的行为"
        },
        {
          "en": "By saying it can talk",
          "zh": "通过说它会说话"
        },
        {
          "en": "By showing it flies",
          "zh": "通过展现它会飞"
        },
        {
          "en": "By making it the villain",
          "zh": "通过把它写成反派"
        }
      ],
      "answer": 0,
      "skill": "Craft and Structure",
      "explain": {
        "en": "The author reveals the llama's gentle, steady nature through its actions as it helps without complaint.",
        "zh": "作者通过羊驼毫无怨言地帮忙的行为，展现了它温和、稳重的天性。"
      }
    },
    {
      "q": {
        "en": "What feeling does the story create at the end?",
        "zh": "故事在结尾营造出怎样的感受？"
      },
      "options": [
        {
          "en": "A happy, satisfied feeling of a job done",
          "zh": "任务完成后的快乐与满足感"
        },
        {
          "en": "A scary feeling of danger",
          "zh": "危险带来的恐惧感"
        },
        {
          "en": "A sad feeling of loss",
          "zh": "失去带来的悲伤"
        },
        {
          "en": "A confusing feeling",
          "zh": "困惑的感觉"
        }
      ],
      "answer": 0,
      "skill": "Author's Purpose and Perspective",
      "explain": {
        "en": "The book ends on a positive note, leaving readers with the warmth of a task completed with help from the llama.",
        "zh": "本书以积极的基调收尾，让读者感受到在羊驼帮助下完成任务的温暖。"
      }
    },
    {
      "q": {
        "en": "Why might the author have chosen a llama instead of a horse?",
        "zh": "作者为什么选择羊驼而不是马？"
      },
      "options": [
        {
          "en": "To make the story unusual and interesting",
          "zh": "为了让故事新奇而有趣"
        },
        {
          "en": "Because horses cannot be rented",
          "zh": "因为马不能被租"
        },
        {
          "en": "Because the story is set on the moon",
          "zh": "因为故事发生在月球上"
        },
        {
          "en": "Because llamas are faster than cars",
          "zh": "因为羊驼比汽车还快"
        }
      ],
      "answer": 0,
      "skill": "Integration of Knowledge and Ideas",
      "explain": {
        "en": "The author picks a llama to give the familiar 'rent an animal' idea a fresh, surprising twist for young readers.",
        "zh": "作者选择羊驼，是为了给“租一只动物”这个熟悉的点子带来新鲜、出人意料的转折，吸引小读者。"
      }
    },
    {
      "q": {
        "en": "What lesson can readers learn from the story?",
        "zh": "读者能从这个故事中学到什么道理？"
      },
      "options": [
        {
          "en": "That help from others makes hard work easier",
          "zh": "他人的帮助能让艰苦的工作变得轻松"
        },
        {
          "en": "That llamas should live alone",
          "zh": "羊驼应该独居"
        },
        {
          "en": "That carrying heavy things is fun",
          "zh": "搬重物很有趣"
        },
        {
          "en": "That you should never ask for help",
          "zh": "永远不应该求助"
        }
      ],
      "answer": 0,
      "skill": "Author's Purpose and Perspective",
      "explain": {
        "en": "Through the family's experience, the story teaches that working together and accepting help makes tough jobs manageable.",
        "zh": "通过这家人的经历，故事告诉我们团结协作、接受帮助能让艰难的工作变得可应付。"
      }
    },
    {
      "q": {
        "en": "How is the book's problem solved?",
        "zh": "书中的问题是如何解决的？"
      },
      "options": [
        {
          "en": "The rented llama carries the load for the family",
          "zh": "租来的羊驼为这家人驮起了行李"
        },
        {
          "en": "A stranger buys them a car",
          "zh": "一位陌生人给他们买了辆汽车"
        },
        {
          "en": "They leave the load behind",
          "zh": "他们把行李丢下了"
        },
        {
          "en": "It starts to rain and washes it away",
          "zh": "开始下雨，把行李冲走了"
        }
      ],
      "answer": 0,
      "skill": "Key Ideas and Details",
      "explain": {
        "en": "The story resolves its problem when the llama takes on the heavy load, letting the family finish their trip.",
        "zh": "故事在羊驼承担起沉重行李、让这家人得以完成旅程时解决了问题。"
      }
    }
  ],
  "extended": {
    "prompt": {
      "en": "If you could rent any animal for a day, which would you pick and what job would it help you with? Draw or write about your idea.",
      "zh": "如果你可以租任何一种动物玩一天，你会选哪种？它会帮你做什么事？画一画或写一写你的想法。"
    },
    "guidance": {
      "en": [
        "Name the animal you would rent.",
        "Describe the job or problem it would help with.",
        "Explain why that animal is a good choice."
      ],
      "zh": [
        "说出你想租的动物。",
        "描述它会帮你完成的工作或解决的问题。",
        "解释为什么选这种动物很合适。"
      ]
    }
  }
}
