{
  "slug": "carlos-s-puzzle",
  "title": "Carlos's Puzzle",
  "titleZh": "卡洛斯的迷宫谜题",
  "level": "T",
  "genre": "Narrative",
  "mainSkill": "Key Ideas and Details",
  "questions": [
    {
      "q": {
        "en": "What is Carlos especially good at?",
        "zh": "卡洛斯特别擅长什么？"
      },
      "options": [
        {
          "en": "Solving mazes",
          "zh": "解迷宫"
        },
        {
          "en": "Playing sports",
          "zh": "体育运动"
        },
        {
          "en": "Painting",
          "zh": "画画"
        },
        {
          "en": "Singing",
          "zh": "唱歌"
        }
      ],
      "answer": 0,
      "skill": "Key Ideas and Details",
      "explain": {
        "en": "The book says Carlos 'was an expert at finding the path from beginning to end without getting lost.'",
        "zh": "书中说卡洛斯“是位专家，能不迷路地从起点找到终点”。"
      }
    },
    {
      "q": {
        "en": "What was the penalty for the brother who finished last in the maze contest?",
        "zh": "迷宫比赛中最后完成的人要受到什么惩罚？"
      },
      "options": [
        {
          "en": "He had to apologize",
          "zh": "他必须道歉"
        },
        {
          "en": "He had to do all the chores in the house for a month",
          "zh": "他必须包揽家里一个月的全部家务"
        },
        {
          "en": "He had to cook dinner according to some versions of the story",
          "zh": "他必须做晚饭（按书中另一种说法）"
        },
        {
          "en": "He had to run a mile",
          "zh": "他必须跑一英里"
        }
      ],
      "answer": 1,
      "skill": "Key Ideas and Details",
      "explain": {
        "en": "Javier suggests 'the last one through the maze does all the chores in the house for a month.'",
        "zh": "哈维尔提议“最后走出迷宫的人包揽家里一个月的全部家务”。"
      }
    },
    {
      "q": {
        "en": "According to Carlos, how is a corn maze made?",
        "zh": "根据卡洛斯的说法，玉米迷宫是怎么做成的？"
      },
      "options": [
        {
          "en": "By cutting paths through stalks in cornfields",
          "zh": "在玉米地里开辟通道，把玉米秆割开"
        },
        {
          "en": "By building walls of stone",
          "zh": "用石头砌墙"
        },
        {
          "en": "By painting lines on the ground according to some versions of the story",
          "zh": "在地面上画线（按书中另一种说法）"
        },
        {
          "en": "By digging tunnels underground",
          "zh": "在地下挖隧道"
        }
      ],
      "answer": 0,
      "skill": "Craft and Structure",
      "explain": {
        "en": "Carlos explains corn mazes are '3-D and made by cutting paths through stalks in cornfields.'",
        "zh": "卡洛斯解释，玉米迷宫是“立体的，通过在玉米地里开辟通道做成”。"
      }
    },
    {
      "q": {
        "en": "What picture was the corn maze designed to show when seen from above?",
        "zh": "从上方俯瞰，这个玉米迷宫被设计成什么图案？"
      },
      "options": [
        {
          "en": "A giant dog",
          "zh": "一只巨大的狗"
        },
        {
          "en": "A map of the farm according to some versions of the story",
          "zh": "农场的地图（按书中另一种说法）"
        },
        {
          "en": "An apple tree full of fruit",
          "zh": "一棵结满果实的苹果树"
        },
        {
          "en": "A football field",
          "zh": "一个足球场"
        }
      ],
      "answer": 2,
      "skill": "Key Ideas and Details",
      "explain": {
        "en": "Carlos knew 'the maze was created to make a picture of an apple tree full of fruit.'",
        "zh": "卡洛斯知道“迷宫被设计成从空中看像一棵结满果实的苹果树”。"
      }
    },
    {
      "q": {
        "en": "Why did Carlos believe he could beat Javier even though Javier is faster?",
        "zh": "既然哈维尔跑得更快，卡洛斯为什么相信自己能赢？"
      },
      "options": [
        {
          "en": "Javier was tired",
          "zh": "哈维尔累了"
        },
        {
          "en": "Carlos is smarter and uses strategy, while Javier just races",
          "zh": "卡洛斯更聪明、讲究策略，而哈维尔只是横冲直撞"
        },
        {
          "en": "The dog helped Carlos according to some versions of the story in an early draft of the book",
          "zh": "狗帮了卡洛斯（按书中另一种说法）（在书的早期草稿中）"
        },
        {
          "en": "Carlos had a map",
          "zh": "卡洛斯有一张地图"
        }
      ],
      "answer": 1,
      "skill": "Integration of Knowledge and Ideas",
      "explain": {
        "en": "Carlos says 'He's faster, but I'm smarter' and plans to 'take our time and think about each of the paths.'",
        "zh": "卡洛斯说“他更快，但我更聪明”，并打算“慢慢来，把每条路都想一想”。"
      }
    },
    {
      "q": {
        "en": "What happened to Javier inside the maze?",
        "zh": "哈维尔在迷宫里发生了什么事？"
      },
      "options": [
        {
          "en": "He got lost forever according to some versions of the story",
          "zh": "他永远迷路了（按书中另一种说法）"
        },
        {
          "en": "He twisted his ankle badly in a hollow in the dirt path",
          "zh": "他在土路的一个坑里严重崴了脚踝"
        },
        {
          "en": "He won the race",
          "zh": "他赢了比赛"
        },
        {
          "en": "He fell asleep",
          "zh": "他睡着了"
        }
      ],
      "answer": 1,
      "skill": "Key Ideas and Details",
      "explain": {
        "en": "The book says Javier 'had twisted his ankle badly in a hollow worn in the dirt path.'",
        "zh": "书中说哈维尔“在土路被踩出的坑里严重崴伤了脚踝”。"
      }
    },
    {
      "q": {
        "en": "What 'dilemma' did Carlos face near the exit?",
        "zh": "在出口附近，卡洛斯面临什么“两难”？"
      },
      "options": [
        {
          "en": "Whether to tell his parents",
          "zh": "要不要告诉父母"
        },
        {
          "en": "Whether to eat or keep walking according to some versions of the story",
          "zh": "要不要吃东西还是继续走（按书中另一种说法）"
        },
        {
          "en": "Whether to win the contest or go back to help his hurt brother",
          "zh": "是去赢比赛，还是回头去帮助受伤的弟弟"
        },
        {
          "en": "Whether to pet the dog",
          "zh": "要不要摸狗"
        }
      ],
      "answer": 2,
      "skill": "Craft and Structure",
      "explain": {
        "en": "Carlos's dilemma was to 'take the final steps to the exit and win' or 'go back to help him.'",
        "zh": "卡洛斯的难题是“走向出口赢下比赛”还是“回头去帮他”。"
      }
    },
    {
      "q": {
        "en": "About how long did it take Carlos to solve the maze before he heard Javier calling?",
        "zh": "在听到哈维尔呼救前，卡洛斯大约花了多久解开迷宫？"
      },
      "options": [
        {
          "en": "About two hours",
          "zh": "大约两小时"
        },
        {
          "en": "About thirty seconds according to some versions of the story",
          "zh": "大约三十秒（按书中另一种说法）"
        },
        {
          "en": "About one day",
          "zh": "大约一整天"
        },
        {
          "en": "About fifteen minutes",
          "zh": "大约十五分钟"
        }
      ],
      "answer": 3,
      "skill": "Key Ideas and Details",
      "explain": {
        "en": "The book says about ten minutes to get close, then 'about another five minutes' to the exit (around 15 total).",
        "zh": "书中说他大约十分钟就接近出口，又“大约五分钟”到达出口（共约15分钟）。"
      }
    },
    {
      "q": {
        "en": "Why did the author include Javier's 'flash of pride' at the end?",
        "zh": "作者为什么在结尾写哈维尔眼中“闪过一丝自豪”？"
      },
      "options": [
        {
          "en": "To show the maze was easy according to some versions of the story in an early draft of the book",
          "zh": "为了表现迷宫很简单（按书中另一种说法）（在书的早期草稿中）"
        },
        {
          "en": "To show Javier cheated",
          "zh": "为了表现哈维尔作弊"
        },
        {
          "en": "To show Javier was angry",
          "zh": "为了表现哈维尔在生气"
        },
        {
          "en": "To show that helping family mattered more to Carlos than winning",
          "zh": "为了表现对卡洛斯来说，帮助家人比赢更重要"
        }
      ],
      "answer": 3,
      "skill": "Author's Purpose and Perspective",
      "explain": {
        "en": "The book says seeing Javier's pride 'was better than winning,' showing the value of family over victory.",
        "zh": "书中说看到哈维尔的自豪“比赢更美好”，体现家人之情重于胜负。"
      }
    },
    {
      "q": {
        "en": "What did Carlos do when he heard Javier calling for help?",
        "zh": "听到哈维尔呼救时，卡洛斯做了什么？"
      },
      "options": [
        {
          "en": "He retraced his steps and went back to help his brother",
          "zh": "他原路返回，去帮助弟弟"
        },
        {
          "en": "He ran straight to the exit",
          "zh": "他直接跑向出口"
        },
        {
          "en": "He called their parents",
          "zh": "他打电话给父母"
        },
        {
          "en": "He ignored it and finished the maze according to some versions of the story",
          "zh": "他置之不理，走完了迷宫（按书中另一种说法）"
        }
      ],
      "answer": 0,
      "skill": "Integration of Knowledge and Ideas",
      "explain": {
        "en": "The book says Carlos 'retraced his steps' and went back after hearing Javier say 'this is no joke!'",
        "zh": "书中说卡洛斯听到哈维尔说“这不是开玩笑！”后“原路返回”去帮他。"
      }
    }
  ],
  "extended": {
    "prompt": {
      "en": "Carlos was about to win when he chose to help Javier instead. Have you ever given up something you wanted to help someone else? Describe the choice and how it felt, like Carlos at the end of the story.",
      "zh": "卡洛斯眼看要赢了，却选择去帮助哈维尔。你有没有曾经放弃自己想要的东西去帮助别人？像故事结尾的卡洛斯那样，讲讲你的选择和当时的感受。"
    },
    "guidance": {
      "en": [
        "Describe the situation and what you gave up.",
        "Explain how you felt, comparing it to Carlos feeling pride was 'better than winning.'"
      ],
      "zh": [
        "描述当时的情形，以及你放弃了什么。",
        "说明你的感受，并与卡洛斯觉得自豪“比赢更美好”作比较。"
      ]
    }
  }
}