{
  "slug": "russia",
  "title": "Russia",
  "titleZh": "俄罗斯",
  "level": "T",
  "genre": "Informational",
  "mainSkill": "Key Ideas and Details",
  "questions": [
    {
      "q": {
        "en": "What is the capital city of Russia?",
        "zh": "俄罗斯的首都是哪座城市？"
      },
      "options": [
        {
          "en": "Moscow",
          "zh": "莫斯科"
        },
        {
          "en": "St. Petersburg",
          "zh": "圣彼得堡"
        },
        {
          "en": "Kiev",
          "zh": "基辅"
        },
        {
          "en": "Siberia",
          "zh": "西伯利亚"
        }
      ],
      "answer": 0,
      "skill": "Key Ideas and Details",
      "explain": {
        "en": "The book states Moscow is Russia's capital city and home to more than twelve million people.",
        "zh": "书中写道，莫斯科是俄罗斯的首都，人口超过一千二百万。"
      }
    },
    {
      "q": {
        "en": "How large is Russia compared to other countries?",
        "zh": "俄罗斯的面积在各国中处于什么地位？"
      },
      "options": [
        {
          "en": "The largest country in the world, almost twice the size of the U.S.",
          "zh": "世界最大的国家，几乎是美国的二倍"
        },
        {
          "en": "The smallest country in Europe",
          "zh": "欧洲最小的国家"
        },
        {
          "en": "About the same size as Japan",
          "zh": "与日本面积差不多"
        },
        {
          "en": "The second largest, after Canada",
          "zh": "第二大，仅次于加拿大"
        }
      ],
      "answer": 0,
      "skill": "Key Ideas and Details",
      "explain": {
        "en": "Russia covers 16,377,742 sq km and is 'the largest country in the world, almost twice the size of the United States.'",
        "zh": "俄罗斯面积16,377,742平方公里，是“世界最大的国家，几乎是美国的二倍”。"
      }
    },
    {
      "q": {
        "en": "What is special about Lake Baikal?",
        "zh": "贝加尔湖有什么特别之处？"
      },
      "options": [
        {
          "en": "It is the oldest and deepest lake in the world",
          "zh": "它是世界上最古老、最深的湖"
        },
        {
          "en": "It is the largest lake in the United States",
          "zh": "它是美国最大的湖"
        },
        {
          "en": "It is a man-made reservoir",
          "zh": "它是一座人造水库"
        },
        {
          "en": "It is frozen all year round",
          "zh": "它终年冰封"
        }
      ],
      "answer": 0,
      "skill": "Key Ideas and Details",
      "explain": {
        "en": "Lake Baikal is 'the oldest and deepest lake in the world' and holds about 20 percent of the world's unfrozen fresh water.",
        "zh": "贝加尔湖是“世界上最古老、最深的湖”，蓄有约全球20%未冻结的淡水。"
      }
    },
    {
      "q": {
        "en": "Which of these is a famous Russian art mentioned in the book?",
        "zh": "书中提到的俄罗斯著名艺术下列哪一项？"
      },
      "options": [
        {
          "en": "The Moscow Ballet and classical music",
          "zh": "莫斯科芭蕾舞团与古典音乐"
        },
        {
          "en": "Broadway musicals",
          "zh": "百老汇音乐剧"
        },
        {
          "en": "Japanese kabuki",
          "zh": "日本歌舞伎"
        },
        {
          "en": "African drumming",
          "zh": "非洲鼓乐"
        }
      ],
      "answer": 0,
      "skill": "Key Ideas and Details",
      "explain": {
        "en": "Russians are 'particularly known for their world-famous Moscow Ballet and classical musicians.'",
        "zh": "俄罗斯人“尤其以世界闻名的莫斯科芭蕾舞团和古典音乐家著称”。"
      }
    },
    {
      "q": {
        "en": "In what year did a revolution end the rule of the czars?",
        "zh": "哪一年发生的革命结束了沙皇的统治？"
      },
      "options": [
        {
          "en": "1917",
          "zh": "1917年"
        },
        {
          "en": "1922",
          "zh": "1922年"
        },
        {
          "en": "1991",
          "zh": "1991年"
        },
        {
          "en": "1762",
          "zh": "1762年"
        }
      ],
      "answer": 0,
      "skill": "Key Ideas and Details",
      "explain": {
        "en": "The book says a revolution in 1917 'ended the rule of the czars.'",
        "zh": "书中说1917年的革命“结束了沙皇的统治”。"
      }
    },
    {
      "q": {
        "en": "What is borscht, a popular Russian food?",
        "zh": "俄罗斯常见食物罗宋汤（borscht）是什么？"
      },
      "options": [
        {
          "en": "A soup made with beets that is red in color",
          "zh": "一种用甜菜做成、呈红色的汤"
        },
        {
          "en": "A drink made from stale bread",
          "zh": "一种用陈面包做的饮料"
        },
        {
          "en": "A type of pancake",
          "zh": "一种薄饼"
        },
        {
          "en": "A kind of meat pie",
          "zh": "一种肉派"
        }
      ],
      "answer": 0,
      "skill": "Key Ideas and Details",
      "explain": {
        "en": "Borscht is 'a popular soup made from beets' and 'gets its red color from the beets.'",
        "zh": "罗宋汤是“用甜菜做成的流行汤品”，其红色“来自甜菜”。"
      }
    },
    {
      "q": {
        "en": "How is the book about Russia organized?",
        "zh": "这本关于俄罗斯的书是如何组织的？"
      },
      "options": [
        {
          "en": "By topics such as People, Land, History, Celebrations, and Food",
          "zh": "按主题分章，如人民、土地、历史、节日和食物"
        },
        {
          "en": "As a day-by-day diary",
          "zh": "以日记形式按天记录"
        },
        {
          "en": "As a list of presidents",
          "zh": "以总统列表形式"
        },
        {
          "en": "In the form of a poem",
          "zh": "以诗歌形式"
        }
      ],
      "answer": 0,
      "skill": "Craft and Structure",
      "explain": {
        "en": "The table of contents shows sections like Where Is It?, People, Land, History, Celebrations, and Food.",
        "zh": "目录显示有“在哪里”“人民”“土地”“历史”“节日”“食物”等章节。"
      }
    },
    {
      "q": {
        "en": "Why does the author include a section on the Cyrillic alphabet?",
        "zh": "作者为什么专门介绍西里尔字母？"
      },
      "options": [
        {
          "en": "To show a unique feature of the Russian language and culture",
          "zh": "为了展现俄罗斯语言与文化的独特之处"
        },
        {
          "en": "To teach readers how to count money",
          "zh": "教读者如何数钱"
        },
        {
          "en": "To explain the weather",
          "zh": "解释天气"
        },
        {
          "en": "To describe the food",
          "zh": "描述食物"
        }
      ],
      "answer": 0,
      "skill": "Author's Purpose and Perspective",
      "explain": {
        "en": "The book explains Russian uses the Cyrillic alphabet with 33 letters, highlighting a special part of its culture.",
        "zh": "书中说明俄语使用有33个字母的西里尔字母，突显了其文化的特色。"
      }
    },
    {
      "q": {
        "en": "Which statement combines facts from the book correctly?",
        "zh": "下列哪一项正确地结合了书中的事实？"
      },
      "options": [
        {
          "en": "Russia borders the Arctic Ocean and has the world's coldest settlement",
          "zh": "俄罗斯濒临北冰洋，并拥有世界上最冷的定居点"
        },
        {
          "en": "Russia is a small, warm country near the equator",
          "zh": "俄罗斯是靠近赤道的小型温暖国家"
        },
        {
          "en": "Most Russians live in the tundra year-round",
          "zh": "多数俄罗斯人常年住在苔原"
        },
        {
          "en": "Russia has no forests at all",
          "zh": "俄罗斯完全没有森林"
        }
      ],
      "answer": 0,
      "skill": "Integration of Knowledge and Ideas",
      "explain": {
        "en": "The book says the Arctic Ocean borders Russia to the north and that it is 'home to the coldest settlement in the world.'",
        "zh": "书中说北冰洋在俄罗斯北部与其接壤，且俄罗斯拥有“世界上最冷的定居点”。"
      }
    },
    {
      "q": {
        "en": "What makes Russia 'unique' according to the book's focus question?",
        "zh": "根据本书的焦点问题，是什么让俄罗斯“独一无二”？"
      },
      "options": [
        {
          "en": "Its vast size, rich resources, and strong traditions",
          "zh": "辽阔的国土、丰富的资源和深厚的传统"
        },
        {
          "en": "Its location on a small island",
          "zh": "它位于一座小岛上"
        },
        {
          "en": "Its lack of any celebrations",
          "zh": "它没有任何节日"
        },
        {
          "en": "Its single language shared with all nations",
          "zh": "它与所有国家共用的单一语言"
        }
      ],
      "answer": 0,
      "skill": "Author's Purpose and Perspective",
      "explain": {
        "en": "The Conclusion says Russia is rich in natural resources, beautiful landscapes, ballet, holidays, and delicious foods—'rich in tradition.'",
        "zh": "结论写道，俄罗斯拥有丰富的自然资源、美丽的风景、芭蕾、节日和美食，“传统深厚”。"
      }
    }
  ],
  "extended": {
    "prompt": {
      "en": "If you could visit Russia, which part of the book would you most want to see—its land, its celebrations, or its food? Plan a pretend visit and explain your choice with facts from the book.",
      "zh": "如果去俄罗斯旅行，书中哪部分你最想亲身体验——它的土地、节日还是美食？请计划一次假想旅行，并用书中的事实说明你的选择。"
    },
    "guidance": {
      "en": [
        "Look at Lake Baikal and the landscapes in the Land section.",
        "Consider Maslenitsa or the food such as borscht and blinis."
      ],
      "zh": [
        "看看“土地”部分的贝加尔湖与各地貌。",
        "想想谢肉节，或罗宋汤、薄饼等食物。"
      ]
    }
  }
}