{
  "slug": "mirroring-miranda",
  "title": "Mirroring Miranda",
  "titleZh": "镜中的米兰达",
  "level": "V",
  "genre": "Narrative",
  "mainSkill": "Craft and Structure",
  "questions": [
    {
      "q": {
        "en": "What is Miranda's big goal at the beginning of the story?",
        "zh": "故事开头，米兰达的大目标是什么？"
      },
      "options": [
        {
          "en": "To win a sports competition",
          "zh": "赢得一场体育比赛"
        },
        {
          "en": "To write a science fiction story that gets published and wins an award",
          "zh": "写一本科幻小说，成功出版并获奖"
        },
        {
          "en": "To become a professional basketball player",
          "zh": "成为职业篮球运动员"
        },
        {
          "en": "To travel to another country",
          "zh": "去另一个国家旅行"
        }
      ],
      "answer": 1,
      "skill": "Key Ideas and Details",
      "explain": {
        "en": "She tells the mirror she will write a sci-fi story that gets published and wins the Hugo or Nebula Award.",
        "zh": "她对镜子说自己要写一本科幻小说，成功出版并赢得雨果奖或星云奖。"
      }
    },
    {
      "q": {
        "en": "Miranda says her story about the giant zucchini that squashed Cincinnati is an example of what literary device?",
        "zh": "米兰达说她那个关于巨型西葫芦压扁辛辛那提的故事，是哪种文学创作手法的例子？"
      },
      "options": [
        {
          "en": "An allegory",
          "zh": "寓言（allegory）"
        },
        {
          "en": "A history report",
          "zh": "历史报告"
        },
        {
          "en": "A math problem",
          "zh": "数学题"
        },
        {
          "en": "A science experiment",
          "zh": "科学实验"
        }
      ],
      "answer": 0,
      "skill": "Craft and Structure",
      "explain": {
        "en": "She says 'We sci-fi writers call this an allegory,' meaning the silly story had a hidden meaning about greedy rulers.",
        "zh": "她说“我们科幻作家称之为寓言”，意思是这个滑稽故事暗含了关于贪婪统治者的寓意。"
      }
    },
    {
      "q": {
        "en": "Who appears to Miranda in her bedroom mirror?",
        "zh": "出现在米兰达卧室镜子中的是谁？"
      },
      "options": [
        {
          "en": "Her brother Harris playing a trick",
          "zh": "她哥哥哈里斯在恶作剧"
        },
        {
          "en": "A famous movie star",
          "zh": "一位著名电影明星"
        },
        {
          "en": "A boy named James Miranda, her spirit twin in a parallel universe",
          "zh": "一个叫詹姆斯·米兰达的男孩，是她平行宇宙里的“精神双胞胎”"
        },
        {
          "en": "The president",
          "zh": "总统"
        }
      ],
      "answer": 2,
      "skill": "Key Ideas and Details",
      "explain": {
        "en": "The boy in the mirror calls himself James Miranda and says they are 'spirit twins' in a backwards parallel world.",
        "zh": "镜中的男孩自称詹姆斯·米兰达，并说他们是在镜像平行世界里的“精神双胞胎”。"
      }
    },
    {
      "q": {
        "en": "How did Miranda decide the order in which she would read the science-fiction authors?",
        "zh": "米兰达是如何决定阅读各位科幻作家作品的顺序的？"
      },
      "options": [
        {
          "en": "In alphabetical order",
          "zh": "按字母顺序"
        },
        {
          "en": "In a random order",
          "zh": "随机决定顺序"
        },
        {
          "en": "By the authors' ages",
          "zh": "按作者年龄"
        },
        {
          "en": "From shortest book to longest",
          "zh": "从最短的书到最长的书"
        }
      ],
      "answer": 1,
      "skill": "Integration of Knowledge and Ideas",
      "explain": {
        "en": "She had an alphabetical list but chose to read the authors randomly because randomness felt more like science fiction.",
        "zh": "她虽然列了字母顺序表，却选择随机阅读，因为随机感更像科幻。"
      }
    },
    {
      "q": {
        "en": "Why does the author include a Glossary at the end of the book?",
        "zh": "作者在书末附上“词汇表”(Glossary)是为了什么？"
      },
      "options": [
        {
          "en": "To list the chapter titles",
          "zh": "列出章节标题"
        },
        {
          "en": "To explain the meanings of story and science-fiction terms used in the book",
          "zh": "解释书中用到的故事与科幻术语的含义"
        },
        {
          "en": "To translate the book into Spanish",
          "zh": "把书翻译成西班牙语"
        },
        {
          "en": "To show the author's photo",
          "zh": "展示作者照片"
        }
      ],
      "answer": 1,
      "skill": "Author's Purpose and Perspective",
      "explain": {
        "en": "The glossary defines words like allegory, fantasy, and science fiction that appear in the story.",
        "zh": "词汇表解释了故事中出现的寓言、幻想、科幻等词语的含义。"
      }
    },
    {
      "q": {
        "en": "Which awards does Miranda hope her story will win?",
        "zh": "米兰达希望她的故事能赢得哪些奖项？"
      },
      "options": [
        {
          "en": "The Oscar and the Grammy",
          "zh": "奥斯卡奖和格莱美奖"
        },
        {
          "en": "The Hugo Award or the Nebula Award",
          "zh": "雨果奖或星云奖"
        },
        {
          "en": "The Nobel Prize",
          "zh": "诺贝尔奖"
        },
        {
          "en": "The Pulitzer Prize",
          "zh": "普利策奖"
        }
      ],
      "answer": 1,
      "skill": "Key Ideas and Details",
      "explain": {
        "en": "She dreams of winning the Hugo, the Nebula, or maybe both - prestigious sci-fi writing awards.",
        "zh": "她梦想赢得雨果奖、星云奖，或两者兼得——这些都是著名的科幻写作奖项。"
      }
    },
    {
      "q": {
        "en": "In the book, what causes the mirror to fog up when Miranda breathes on it?",
        "zh": "在书中，米兰达对着镜子哈气时，镜子为什么会起雾？"
      },
      "options": [
        {
          "en": "Condensation - breath (water vapor) turns to liquid on the cold surface",
          "zh": "凝结——呵出的水汽在冷表面变成了液体"
        },
        {
          "en": "Paint on the mirror",
          "zh": "镜子上的油漆"
        },
        {
          "en": "A magic spell",
          "zh": "魔法咒语"
        },
        {
          "en": "Dust in the air",
          "zh": "空气中的灰尘"
        }
      ],
      "answer": 0,
      "skill": "Craft and Structure",
      "explain": {
        "en": "The glossary defines condensation as changing from gas to liquid, such as water vapor to water.",
        "zh": "词汇表把凝结定义为从气体变为液体，例如水汽变成水。"
      }
    },
    {
      "q": {
        "en": "What kind of stories does Miranda's brother Harris think she should write instead of science fiction?",
        "zh": "米兰达的哥哥哈里斯认为她应该写什么样的故事，而不是科幻？"
      },
      "options": [
        {
          "en": "Lost kittens, pink princesses, and wild horses",
          "zh": "走失的小猫、粉红公主和野马"
        },
        {
          "en": "Space adventures",
          "zh": "太空冒险"
        },
        {
          "en": "Mystery detectives",
          "zh": "侦探悬疑"
        },
        {
          "en": "Cooking recipes",
          "zh": "烹饪食谱"
        }
      ],
      "answer": 0,
      "skill": "Integration of Knowledge and Ideas",
      "explain": {
        "en": "Harris tells her to leave sci-fi to boys and write about lost kittens, pink princesses, and wild horses.",
        "zh": "哈里斯叫她把科幻留给男孩，去写走失的小猫、粉红公主和野马。"
      }
    },
    {
      "q": {
        "en": "What is the title of the bestselling book Miranda finally publishes?",
        "zh": "米兰达最终出版的那本畅销书叫什么名字？"
      },
      "options": [
        {
          "en": "Pen Pal in the Looking Glass",
          "zh": "《镜子里的笔友》"
        },
        {
          "en": "The Mutant Zucchini",
          "zh": "《变异西葫芦》"
        },
        {
          "en": "Future Tense",
          "zh": "《未来时态》"
        },
        {
          "en": "Journey to the Center of the Earth",
          "zh": "《地心游记》"
        }
      ],
      "answer": 0,
      "skill": "Key Ideas and Details",
      "explain": {
        "en": "Her journal grew into Pen Pal in the Looking Glass, a bestseller about the mirror world.",
        "zh": "她的日记扩展成了畅销书《镜子里的笔友》，讲述镜中世界的故事。"
      }
    },
    {
      "q": {
        "en": "What did critics say about Miranda's published story?",
        "zh": "评论家对米兰达出版的故事是怎么评价的？"
      },
      "options": [
        {
          "en": "It was too hard to understand",
          "zh": "太难懂了"
        },
        {
          "en": "It blended science with fiction so well that it was hard to tell where one ended and the other began",
          "zh": "它把科学和虚构结合得极好，让人难以区分科学与虚构的界限"
        },
        {
          "en": "It should have been a textbook",
          "zh": "本该写成教科书"
        },
        {
          "en": "It was too short",
          "zh": "太短了"
        }
      ],
      "answer": 1,
      "skill": "Author's Purpose and Perspective",
      "explain": {
        "en": "Critics said she blended science and fiction so well that the line between them was hard to see.",
        "zh": "评论家说她把科学和虚构结合得太好，两者之间的界限难以分辨。"
      }
    }
  ],
  "extended": {
    "prompt": {
      "en": "If you could receive a message from a version of yourself in a parallel universe, what would you want to tell - or learn from - that other you?",
      "zh": "如果你能从平行宇宙里的另一个“自己”那里收到一条信息，你最想告诉那个自己什么，又想从他/她身上学到什么？"
    },
    "guidance": {
      "en": [
        "Think about a goal you care about and how a 'mirror twin' might encourage or challenge you.",
        "Use details from Miranda's experience to inspire your ideas."
      ],
      "zh": [
        "想一个你在意的目标，并思考“镜中双胞胎”会怎样鼓励或挑战你。",
        "可以借用米兰达的经历来激发你的想法。"
      ]
    }
  }
}